<?xml version="1.0" encoding="UTF-8"?>
<root>
  <uid>2</uid>
  <datetime>2012-08-24 12:03:37</datetime>
  <title>几个流行的Linux发行版，附下载地址</title>
  <content>&lt;p&amp;nbsp;style=\"text-indent:2em;\"&gt;
	最近听说Linux系统很好,&amp;nbsp;超越了Windows,&amp;nbsp;而且是免费的.&amp;nbsp;我想试一试.&amp;nbsp;因为这样我就可以摆脱微软的控制了,&amp;nbsp;我虽然用的是盗版Windows,&amp;nbsp;但我并不觉得自己赚了便宜.&amp;nbsp;我一直在微软帝国的控制之下.
&lt;/p&gt;
&lt;p&amp;nbsp;style=\"text-indent:2em;\"&gt;
	这里的标题就是Linux操作系统下载。
&lt;/p&gt;
&lt;p&amp;nbsp;style=\"text-indent:2em;\"&gt;
	最近心情好身体也不错,&amp;nbsp;也想蹦跶几下.&amp;nbsp;所以下用Linux,&amp;nbsp;Linux是免费的,&amp;nbsp;不过要有光盘或自己在网上下载.&amp;nbsp;&amp;nbsp;网上下载是免费的.&amp;nbsp;不过找下载地址似乎不是那么容易哦.
&lt;/p&gt;
&lt;p&amp;nbsp;style=\"text-indent:2em;\"&gt;
	我是做网页的.&amp;nbsp;碰巧有个闲置的域名,&amp;nbsp;我想,&amp;nbsp;我收集一些流行度比较高的linux发行版的下载地址.&amp;nbsp;&amp;nbsp;这样大家要是想下载linux,&amp;nbsp;也不用东找西找,&amp;nbsp;浪费时间了.
&lt;/p&gt;
&lt;p&amp;nbsp;style=\"text-indent:2em;\"&gt;
	希望我的努力能够给大家一些方便!
&lt;/p&gt;
&lt;p&amp;nbsp;style=\"text-indent:2em;\"&gt;
	1.&amp;nbsp;Ubuntu&amp;nbsp;Linux&amp;nbsp;操作系统下载地址:
&lt;/p&gt;
&lt;p&amp;nbsp;style=\"text-indent:2em;\"&gt;
	Ubuntu现在最最流行了,&amp;nbsp;社区支持也不错.&amp;nbsp;&amp;nbsp;有问题也可以在网上找到答案,&amp;nbsp;推荐使用!&amp;nbsp;最新11.04版下载地址:
&lt;/p&gt;
&lt;p&amp;nbsp;style=\"text-indent:2em;\"&gt;
	&lt;a&amp;nbsp;href=\"http://yfdisk.com/file/yfiscool/c1365a33/\"&amp;nbsp;target=\"_blank\"&gt;下载：&amp;nbsp;ubuntu-11.04-desktop-i386.iso&lt;/a&gt;
&lt;/p&gt;
&lt;p&amp;nbsp;style=\"text-indent:2em;\"&gt;
	（进去后点“普通下载”然后等待30秒即可免费下载）
&lt;/p&gt;
&lt;p&amp;nbsp;style=\"text-indent:2em;\"&gt;
	2.&amp;nbsp;Debian&amp;nbsp;Linux&amp;nbsp;操作系统下载地址:
&lt;/p&gt;
&lt;p&amp;nbsp;style=\"text-indent:2em;\"&gt;
	Debian是最最经典也是最最Linux的Linux系统了,&amp;nbsp;Ubuntu也是基于Debian开发的,&amp;nbsp;我就最喜欢用它最服务器系统了,&amp;nbsp;非常稳定!&amp;nbsp;官方下载地址是:
&lt;/p&gt;
&lt;p&amp;nbsp;style=\"text-indent:2em;\"&gt;
	&lt;a&amp;nbsp;href=\"http://www.debian.org/CD/http-ftp/\"&amp;nbsp;target=\"_blank\"&gt;http://www.debian.org/CD/http-ftp/&amp;nbsp;&lt;/a&gt;这里有世界各地的镜像站点,&amp;nbsp;自己选个快点的吧.
&lt;/p&gt;
&lt;p&amp;nbsp;style=\"text-indent:2em;\"&gt;
	3.&amp;nbsp;Fedora&amp;nbsp;Linux系统下载地址:
&lt;/p&gt;
&lt;p&amp;nbsp;style=\"text-indent:2em;\"&gt;
	Fedora是曾经Redhat的延续,&amp;nbsp;我的处女安装就献给它了.&amp;nbsp;不过后来Redhat企业版收费了,&amp;nbsp;Redhat公司出了免费的Fedora.&amp;nbsp;不过我已经转战Ubuntu了,&amp;nbsp;不过如果你喜欢,我当然要给你下载地址了:
&lt;/p&gt;
&lt;p&amp;nbsp;style=\"text-indent:2em;\"&gt;
	&lt;a&amp;nbsp;href=\"http://fedoraproject.org/get-fedora\"&amp;nbsp;target=\"_blank\"&gt;http://fedoraproject.org/get-fedora&lt;/a&gt;
&lt;/p&gt;
&lt;p&amp;nbsp;style=\"text-indent:2em;\"&gt;
	4.&amp;nbsp;CentOS&amp;nbsp;系统下载地址:
&lt;/p&gt;
&lt;p&amp;nbsp;style=\"text-indent:2em;\"&gt;
	刚才说过了,&amp;nbsp;Redhat企业版已经收费了.&amp;nbsp;&amp;nbsp;不过由于linux/gnu协议的限制,&amp;nbsp;它仍然是开放源码的.&amp;nbsp;所以就有linux热心人用它的源码重新编译，&amp;nbsp;这就是CentOS.&amp;nbsp;CentOS可以说跟Redhat&amp;nbsp;Enterprise一模一样的，唯一不同的是它不能享受Redhat的技术服务。
&lt;/p&gt;
&lt;p&amp;nbsp;style=\"text-indent:2em;\"&gt;
	&lt;a&amp;nbsp;href=\"http://mirrors.163.com/centos/5.4/isos/i386/\"&amp;nbsp;target=\"_blank\"&gt;http://mirrors.163.com/centos/5.4/isos/i386/&amp;nbsp;&lt;/a&gt;网易镜像下载,&amp;nbsp;速度比较快
&lt;/p&gt;
&lt;p&amp;nbsp;style=\"text-indent:2em;\"&gt;
	5.&amp;nbsp;红旗Redflag&amp;nbsp;Linux操作系统下载地址：
&lt;/p&gt;
&lt;p&amp;nbsp;style=\"text-indent:2em;\"&gt;
	记住，Redflag是红旗哦，&amp;nbsp;红旗是国产的。是国产精品哦。大家要支持哦。官方下载地址是：
&lt;/p&gt;
&lt;p&amp;nbsp;style=\"text-indent:2em;\"&gt;
	&lt;a&amp;nbsp;href=\"http://www.qq73.com/a/4#mce_temp_url#\"&amp;nbsp;target=\"_blank\"&gt;http://www.redflag-linux.com/d/iso/&lt;/a&gt;
&lt;/p&gt;
&lt;p&amp;nbsp;style=\"text-indent:2em;\"&gt;
	转载自：
&lt;/p&gt;
&lt;p&amp;nbsp;style=\"text-indent:2em;\"&gt;
	Linux操作系统下载&amp;nbsp;http://www.qq73.com
&lt;/p&gt;</content>
  <contentx>最近听说Linux系统很好, 超越了Windows, 而且是免费的. 我想试一试. 因为这样我就可以摆脱微软的控制了, 我虽然用的是盗版Windows, 但我并不觉得自己赚了便宜. 我一直在微软帝国的控制之下.


	这里的标题就是Linux操作系统下载。


	最近心情好身体也不错, 也想蹦跶几下. 所以下用Linux, Linux是免费的, 不过要有光盘</contentx>
  <tags>_null_</tags>
</root>
