{"author":"DANGTONG","uid":"16","type":"php","stype":"php","date":"2012-06-13 13:37:06","artid":388,"readInfo":"0*81","title":"php\u535a\u5ba2wordpress\u4f2a\u9759\u6001\u5b9e\u73b0\u65b9\u6cd5","path":"1339565869.xml","contentx":"\u9996\u5148\u8fd8\u662f\u8bf4\u4e0b\u8be5php\u535a\u5ba2wordpress\u7684\u73af\u5883\u914d\u7f6e\uff1aLinux\u64cd\u4f5c\u7cfb\u7edf+Nginx\u7f51\u9875\u670d\u52a1\u5668(\u4e0d\u662fApache\u670d\u52a1\u5668)+php+mysql=\u6211\u7684Wordpress\u535a\u5ba2\u4e4b\u524d\u4e00\u76f4\u6ca1\u6709\u4fee\u6539URL\u914d\u7f6e\uff0c\u5c31\u662f\u7528\u7684\u9ed8\u8ba4\u7684\u94fe\u63a5\uff0c\u94fe\u63a5\u683c\u5f0f\u662f\uff1ahttp:\/\/www.phpboke.com\/index.php\/2010\/11\/01\/sample-post\/\u7ec8\u4e8e\u6709\u4e00\u5929\u770b\u8fd9\u4e2a\u5730\u5740...","lastModify":"2012-06-20 19:30:33"}