[{"fu":"120","ct":"<ol>\n\t<li>\n\t\t<span style=\\\"font-size:12px;line-height:1.5;\\\"><\/span><span style=\\\"font-size:12px;line-height:1.5;\\\">\u5f88\u597d<\/span>\n\t<\/li>\n\t<li>\n\t\t<span style=\\\"font-size:12px;line-height:1.5;\\\">\u975e\u5e38\u597d<\/span>\n\t<\/li>\n\t<li>\n\t\t<span style=\\\"font-size:12px;line-height:1.5;\\\">\u975e\u5e38\u975e\u5e38\u597d<\/span>\n\t<\/li>\n\t<li>\n\t\t<span style=\\\"font-size:12px;line-height:1.5;\\\">\u597d\u7684\u4e0d\u884c\u4e86\u554a<\/span>\n\t<\/li>\n\t<li>\n\t\t<span style=\\\"font-size:12px;line-height:1.5;\\\">........<\/span>\n\t<\/li>\n<\/ol>","dt":"2013-03-07 17:11:23","pd":"302"},{"fu":"2","ct":"............","dt":"2013-03-07 18:51:41","pd":"302"},{"fu":"2","ct":"<img src=\\\"\/mod\/kd\/plugins\/emoticons\/images\/jx2\/j_0025.gif\\\" border=\\\"0\\\" alt=\\\"\\\" \/>","dt":"2013-03-19 21:23:23","pd":"302"},{"fu":"2","ct":"<img src=\\\"\/mod\/kd\/plugins\/emoticons\/images\/jx2\/j_0025.gif\\\" border=\\\"0\\\" alt=\\\"\\\" \/>","dt":"2013-03-19 21:23:28","pd":"302"},{"fu":"2","ct":"<img src=\\\"\/mod\/kd\/plugins\/emoticons\/images\/jx2\/j_0025.gif\\\" border=\\\"0\\\" alt=\\\"\\\" \/>","dt":"2013-03-19 21:23:48","pd":"302"}]