<?xml version="1.0" encoding="UTF-8"?>
<root>
<title>360华为合作顺利 首款360特供机七月预订</title>
<content>&amp;lt;p&amp;gt;
	6月2日消息，360用户特供机的官方发消息称，与华为合作进展顺利，首款360用户特供机华为闪耀（双核）将于七月预订，同时360特供机还会陆续推出更多款高性价比手机。据悉，为保障特供机质量，360从三个方面挑选合作伙伴：质量管控方面，要有数年手机制造经验；保证年出货率暴涨有500万&amp;nbsp;-1000&amp;nbsp;万台；合作伙伴应具备全国范围的售后、换货及维修网络，以保证用户得到完善的服务。最终选择了华为，目前双方合作顺利，首款360用户特供机华为闪耀（双核）将于七月预订。
&amp;lt;/p&amp;gt;
&amp;lt;p&amp;nbsp;style=\"text-align:center;\"&amp;gt;
	&amp;lt;img&amp;nbsp;src=\"http://upload.chinaz.com/2012/0602/1338616294370.jpg\"&amp;nbsp;alt=\"\"&amp;nbsp;/&amp;gt;&amp;nbsp;
&amp;lt;/p&amp;gt;
&amp;lt;p&amp;nbsp;style=\"text-align:center;\"&amp;gt;
	&amp;lt;br&amp;nbsp;/&amp;gt;
&amp;lt;/p&amp;gt;
&amp;lt;p&amp;gt;
	360用户特供机的官方发消息：首款&amp;nbsp;360特供机华为闪耀（双核）将于七月预订
&amp;lt;/p&amp;gt;
&amp;lt;p&amp;gt;
	关于渠道方面，周鸿祎在微博中称，&amp;nbsp;360&amp;nbsp;用户特供机是由厂商通过电商渠道直接卖给用户，&amp;nbsp;360不从销售中拿一分钱，&amp;nbsp;360所做的就是替用户拼命压价。
&amp;lt;/p&amp;gt;
&amp;lt;p&amp;gt;
	此外，360&amp;nbsp;董事长周鸿祎出席“&amp;nbsp;CHINICT&amp;nbsp;科技明星在中国”时表示，360&amp;nbsp;特供手机将在一两个月内推出，将基于Android4.0系统进行优化，会预置360桌面、360手机卫士等产品。
&amp;lt;/p&amp;gt;
&amp;lt;p&amp;gt;
	而华为终端公司董事长余承东也曾披露360&amp;nbsp;特供手机会在六月量产，在七月份开始接受预订。
&amp;lt;/p&amp;gt;
&amp;lt;p&amp;gt;
	据介绍，360特供手机装载了4.3&amp;nbsp;英寸触控屏，支持qHD（960×540像素）分辨率，搭载Android4.0系统，并有1GB&amp;nbsp;的RAM容量和4GB&amp;nbsp;的ROM&amp;nbsp;存储空间。为实现实现视频通话和自拍功能，该机也采用了双镜头配置：30万像素前置镜头和500万像素主镜头，支持自动聚焦和高清视频录制等功能。
&amp;lt;/p&amp;gt;
&amp;lt;p&amp;gt;
	&amp;lt;br&amp;nbsp;/&amp;gt;
&amp;lt;/p&amp;gt;</content>
<json-link>./file/news/2012-06-03/1338687010.json</json-link>
<comment-link>4</comment-link>
<tags>5</tags>
<imghref/>
<comment-list>
 <c>
  <author-c>1</author-c>
  <uid-c>2</uid-c>
  <date-c>2</date-c>
  <conf-c>3</conf-c>
  <locked>true</locked>
 </c>
</comment-list>
</root>
