[{"fu":"66","ct":"\u6c99\u53d1\u81ea\u5df1\u5750&lt;img&amp;nbsp;src=\\\"\/mod\/kd\/plugins\/emoticons\/images\/jx2\/j_0017.gif\\\"&amp;nbsp;border=\\\"0\\\"&amp;nbsp;alt=\\\"\\\"&amp;nbsp;\/&gt;","dt":"2012-08-17 17:47:26","pd":"29"},{"fu":"66","ct":"\u5475\u5475\uff0c\u81ea\u5df1\u9876\u4e00\u9876\uff0c\u771f\u662f\u592a\u4e0d\u597d\u610f\u601d\u4e86&lt;img&amp;nbsp;src=\\\"\/mod\/kd\/plugins\/emoticons\/images\/jx2\/j_0035.gif\\\"&amp;nbsp;border=\\\"0\\\"&amp;nbsp;alt=\\\"\\\"&amp;nbsp;\/&gt;","dt":"2012-08-17 17:48:34","pd":"29"},{"fu":"66","ct":"\u5750\u7b49\u697c\u4e0b\u5e05\u54e5\u505a\u6211\u5934\u53f7\u7c89\u4e1d&lt;img&amp;nbsp;src=\\\"\/mod\/kd\/plugins\/emoticons\/images\/jx2\/j_0007.gif\\\"&amp;nbsp;border=\\\"0\\\"&amp;nbsp;alt=\\\"\\\"&amp;nbsp;\/&gt;","dt":"2012-08-17 17:49:17","pd":"29"},{"fu":"2","ct":"\u6211\u53c9&amp;nbsp;chmod&amp;nbsp;000&amp;nbsp;\u4f60","dt":"2012-08-17 18:03:14","pd":"29"},{"fu":"29","ct":"&lt;img&amp;nbsp;src=\\\"\/mod\/kd\/plugins\/emoticons\/images\/tsj\/t_0023.gif\\\"&amp;nbsp;border=\\\"0\\\"&amp;nbsp;alt=\\\"\\\"&amp;nbsp;\/&gt;","dt":"2012-08-17 19:56:56","pd":"29"},{"fu":"2","ct":"&lt;img&amp;nbsp;src=\\\"\/mod\/kd\/plugins\/emoticons\/images\/youa\/y_0020.gif\\\"&amp;nbsp;border=\\\"0\\\"&amp;nbsp;alt=\\\"\\\"&amp;nbsp;\/&gt;","dt":"2012-08-17 19:59:20","pd":"29"},{"fu":"19","ct":"\u4f60\u843d\u4f0d\u4e86\u554a\uff01&lt;img&amp;nbsp;src=\\\"\/mod\/kd\/plugins\/emoticons\/images\/jx2\/j_0016.gif\\\"&amp;nbsp;border=\\\"0\\\"&amp;nbsp;alt=\\\"\\\"&amp;nbsp;\/&gt;","dt":"2012-09-01 12:48:41","pd":"29","sub":[{"fu":"66","fun":"%E5%BD%B1%E5%AD%90","ct":"\u7f8e\u5973\u54ea\u4f4d\u554a\uff1f","2u":"19","2un":"Serria","dt":"2012-09-06 19:41:45"},{"fu":"2","fun":"koodo","ct":"\u4f60\u5ac2\u5b50","2u":"66","2un":"\u5f71\u5b50","dt":"2012-09-10 09:34:58"}]}]